<?xml version="1.0" encoding="UTF-8"?>
<Document>
<TEXT>RT @BoschPresse: #<NODE id="18" />Bosch Sensortec<NODE id="33" /> brings <NODE id="41" />intelligent sensors<NODE id="60" /> to smartphones https://t.co/YB3mXSKgN8 #CES2016 #BoschCES https://t.co/Xns2eHb…
</TEXT>
<Meta>
<feature featureName="id" featureValue="vico/7ec55af6-cf5e-3bf5-936d-d75e5d5cab5d" />
<feature featureName="source" featureValue="sensor_corpus" />
<feature featureName="lang" featureValue="en" />
<feature featureName="pubDate" featureValue="2016-01-07T16:40:40Z" />
<feature featureName="indexDate" featureValue="2016-07-13T11:23:09.257Z" />
<feature featureName="uri" featureValue="http://twitter.com/BennoDillinger/statuses/685108797430493185" />
<feature featureName="solrEventType" featureValue="None" /></Meta><Entities>
<Entity id="0" startPos="18" endPos="33" type="organization-company" surface="Bosch Sensortec" />
<Entity id="1" startPos="41" endPos="60" type="product-class" surface="intelligent sensors" /></Entities><Relations>
<Relation id="2" NAME="CompanyProvidesProduct">
<Entity id="1" label="product" />
<Entity id="0" label="company" />
</Relation></Relations>
</Document>
