<?xml version="1.0" encoding="UTF-8"?>
<Document>
<TEXT>Can smart sensors change the #HVAC business? https://t.co/qX0C5BZBrW
</TEXT>
<Meta>
<feature featureName="id" featureValue="vico/3bdf63c5-bf4d-3891-91f6-60bd6b00dc6b" />
<feature featureName="source" featureValue="sensor_corpus" />
<feature featureName="lang" featureValue="en" />
<feature featureName="pubDate" featureValue="2016-01-12T15:03:14Z" />
<feature featureName="indexDate" featureValue="2016-07-13T10:57:52.85Z" />
<feature featureName="uri" featureValue="http://twitter.com/FabricatedProds/statuses/686896216572059648" />
<feature featureName="solrEventType" featureValue="None" /></Meta><Entities /><Relations />
</Document>
